tornadoshortener/__init__.py
tornadoshortener/app.py
tornadoshortener/handler.py
tornadoshortener/utils.py
tornadoshortener/templates/redirect.android.fallback.html
tornadoshortener/templates/redirect.android.html
tornadoshortener/templates/redirect.ios.fallback.html
tornadoshortener/templates/redirect.ios.html
tornadoshortener-3.0.0.dist-info/AUTHORS
tornadoshortener-3.0.0.dist-info/LICENSE
tornadoshortener-3.0.0.dist-info/METADATA
tornadoshortener-3.0.0.dist-info/WHEEL
tornadoshortener-3.0.0.dist-info/entry_points.txt
tornadoshortener-3.0.0.dist-info/pbr.json
tornadoshortener-3.0.0.dist-info/top_level.txt
tornadoshortener-3.0.0.dist-info/RECORD
