Metadata-Version: 2.1
Name: tornadoshortener
Version: 3.0.0
Summary: UNKNOWN
Home-page: https://github.com/nellessen/tornado-shortener
Author: David Nellessen
Author-email: davidnellessen@gmail.com
License: UNKNOWN
Platform: UNKNOWN
Classifier: Development Status :: 5 - Production/Stable
Classifier: Environment :: Web Environment
Classifier: License :: Other/Proprietary License
Classifier: Operating System :: POSIX :: Linux
Classifier: Programming Language :: Python
Classifier: Programming Language :: Python :: 3
Classifier: Programming Language :: Python :: 3.8
Requires-Dist: hashids (==1.3.1)
Requires-Dist: redis (==3.5.3)
Requires-Dist: tornado (==6.0.4)
